__tests__/__init__.py
__tests__/test_client.py
lulu_api/__init__.py
lulu_api/client.py
lulu_api/exceptions.py
lulu_api/models.py
lulu_api-0.1.1.dist-info/METADATA
lulu_api-0.1.1.dist-info/WHEEL
lulu_api-0.1.1.dist-info/top_level.txt
lulu_api-0.1.1.dist-info/RECORD
